pygmc/__init__.py
pygmc/cli.py
pygmc/history.py
pygmc/connection/__init__.py
pygmc/connection/connection.py
pygmc/connection/const.py
pygmc/connection/discovery.py
pygmc/connection/udev_rule_check.py
pygmc/connection/utils.py
pygmc/device_config/__init__.py
pygmc/devices/__init__.py
pygmc/devices/auto_get_device.py
pygmc/devices/device.py
pygmc/devices/device_rfc1201.py
pygmc/devices/device_rfc1801.py
pygmc/devices/device_spec404.py
pygmc/devices/gmc300.py
pygmc/devices/gmc320.py
pygmc/devices/gmc500.py
pygmc/devices/gmc600.py
pygmc/devices/gmc800.py
pygmc/devices/gmcse.py
pygmc-0.14.1.dist-info/LICENSE
pygmc-0.14.1.dist-info/METADATA
pygmc-0.14.1.dist-info/WHEEL
pygmc-0.14.1.dist-info/entry_points.txt
pygmc-0.14.1.dist-info/top_level.txt
pygmc-0.14.1.dist-info/RECORD
