Metadata-Version: 2.1
Name: pygmc
Version: 0.14.1
Summary: Python package for Geiger–Müller Counter (GMC)
Author: Thomaz
License: MIT License
Project-URL: Homepage, https://github.com/Wikilicious/pygmc
Project-URL: Documentation, https://pygmc.readthedocs.io/
Project-URL: Source, https://github.com/Wikilicious/pygmc
Project-URL: Tracker, https://github.com/Wikilicious/pygmc/issues
Classifier: Programming Language :: Python
Classifier: Programming Language :: Python :: 3.7
Classifier: Programming Language :: Python :: 3.8
Classifier: Programming Language :: Python :: 3.9
Classifier: Programming Language :: Python :: 3.10
Classifier: Programming Language :: Python :: 3.11
Classifier: Programming Language :: Python :: 3.12
Classifier: Topic :: Scientific/Engineering
Classifier: Topic :: Scientific/Engineering :: Physics
Classifier: Topic :: System :: Hardware :: Universal Serial Bus (USB)
Requires-Python: >=3.7
License-File: LICENSE
Requires-Dist: pyserial>=3.4
